dingdong_sonos/__init__.py
dingdong_sonos/_version.py
dingdong_sonos/main.py
dingdong_sonos/media/attention.mp3
dingdong_sonos/media/fanfare.mp3
dingdong_sonos/media/pornhub.mp3
dingdong_sonos/media/quack.mp3
dingdong_sonos/media/sbb.mp3
dingdong_sonos/media/school-bell-sound.mp3
dingdong_sonos/media/wrong.mp3
dingdong_sonos-0.1.7.dist-info/METADATA
dingdong_sonos-0.1.7.dist-info/WHEEL
dingdong_sonos-0.1.7.dist-info/entry_points.txt
dingdong_sonos-0.1.7.dist-info/top_level.txt
dingdong_sonos-0.1.7.dist-info/RECORD
