Metadata-Version: 2.1
Name: dingdong-sonos
Version: 0.1.7
Summary: Ring the Gong
Author-email: Tim Rohner <info@timrohner.ch>
Project-URL: Source, https://github.com/leokster/dingdong_sonos
Keywords: dingdong_sonos
Classifier: Development Status :: 2 - Pre-Alpha
Classifier: Intended Audience :: Developers
Classifier: License :: OSI Approved :: MIT License
Classifier: Natural Language :: English
Classifier: Programming Language :: Python :: 3
Classifier: Programming Language :: Python :: 3.6
Classifier: Programming Language :: Python :: 3.7
Classifier: Programming Language :: Python :: 3.8
Requires-Dist: click ==8.1.3
Requires-Dist: gTTS ==2.4.0
Requires-Dist: mutagen ==1.47.0
Requires-Dist: soco >=0.29.1
Provides-Extra: dev
Requires-Dist: build >=0.10.0 ; extra == 'dev'
Requires-Dist: setuptools-scm >=7.1.0 ; extra == 'dev'
